gfluent/__init__.py
gfluent/bq.py
gfluent/gcs.py
gfluent/sheet.py
gfluent-1.2.1.dist-info/LICENSE
gfluent-1.2.1.dist-info/METADATA
gfluent-1.2.1.dist-info/WHEEL
gfluent-1.2.1.dist-info/top_level.txt
gfluent-1.2.1.dist-info/RECORD
