Metadata-Version: 2.1
Name: gfluent
Version: 1.2.1
Summary: A lightweight wrapper for GCS and BigQuery client library
Home-page: https://github.com/simple-dev-tools/gfluent
Author: Zhong Dai
Author-email: zhongdai.au@gmail.com
License: UNKNOWN
Keywords: google cloud bigquery gcs
Platform: UNKNOWN
Classifier: Development Status :: 2 - Pre-Alpha
Classifier: Intended Audience :: Developers
Classifier: Natural Language :: English
Classifier: Programming Language :: Python :: 3
Classifier: Programming Language :: Python :: 3.8
Classifier: Programming Language :: Python :: 3.9
Classifier: Programming Language :: Python :: 3.10
Requires-Python: >=3.7.3
Requires-Dist: google-api-python-client (==2.36.0)
Requires-Dist: google-cloud-bigquery (==2.32.0)
Requires-Dist: google-cloud-storage (==2.1.0)
